mavcom/__init__.py
mavcom/loracon.py
mavcom/mavconstants.py
mavcom/mavcontrol.py
mavcom/video.py
mavcom-1.1.8.dist-info/LICENSE
mavcom-1.1.8.dist-info/METADATA
mavcom-1.1.8.dist-info/WHEEL
mavcom-1.1.8.dist-info/entry_points.txt
mavcom-1.1.8.dist-info/top_level.txt
mavcom-1.1.8.dist-info/RECORD
