Metadata-Version: 2.2
Name: mavcom
Version: 1.1.8
Summary: A python package that creates a simplified programming interface for controlling Mavlink-capable flight controllers
Author-email: ArduCrow <arducrow@xee4c.33mail.com>
License: MIT License
Project-URL: Homepage, https://github.com/ArduCrow/Mavcom
Keywords: mavlink,drone,drones,pymavlink,dronekit
Classifier: License :: OSI Approved :: MIT License
Classifier: Programming Language :: Python
Classifier: Programming Language :: Python :: 3
Requires-Python: >=3.9
License-File: LICENSE
Requires-Dist: pymavlink
Requires-Dist: pyserial
Provides-Extra: dev
Requires-Dist: black; extra == "dev"
Requires-Dist: pip-tools; extra == "dev"
Requires-Dist: pytest; extra == "dev"
